[
  {
    "id": "1",
    "version": "v3.0",
    "title": "NeurOasis Organization & Complete Project Migration",
    "type": "major",
    "project": "core",
    "date": "2025-05-26",
    "description": "Established GitHub Teams organization and successfully migrated all personal projects to focused repositories with proven template",
    "changes": [
      {
        "type": "new",
        "description": "NeurOasis GitHub Teams organization with proper permissions ($16/month)"
      },
      {
        "type": "new",
        "description": "5 successful project forks: sailing-tools, coffee-recipes, family-tools, budget-nodepad, action-organizer"
      },
      {
        "type": "improved",
        "description": "Repository forking template proven 100% across all project types"
      },
      {
        "type": "improved",
        "description": "Core repository reduced to <30% project knowledge for longer conversations"
      }
    ],
    "created": "2025-05-26T19:35:00.000Z"
  },
  {
    "id": "2",
    "version": "v2.5",
    "title": "Complete Repository Audit & Cleanup",
    "type": "minor",
    "project": "core",
    "date": "2025-05-26",
    "description": "Systematic audit and cleanup of core repository structure with personal context migration",
    "changes": [
      {
        "type": "removed",
        "description": "All personal contexts from staging folder"
      },
      {
        "type": "improved",
        "description": "Clean separation of core GARDEN vs project-specific content"
      },
      {
        "type": "new",
        "description": "Comprehensive audit checklist and systematic cleanup process"
      },
      {
        "type": "improved",
        "description": "Repository structure optimized for project knowledge efficiency"
      }
    ],
    "created": "2025-05-26T19:35:00.000Z"
  },
  {
    "id": "3",
    "version": "v2.2",
    "title": "Repository Forking Strategy & Template",
    "type": "minor",
    "project": "deploy",
    "date": "2025-05-25",
    "description": "Established and documented repository forking workflow with surgical cleanup methodology",
    "changes": [
      {
        "type": "new",
        "description": "CIT_NeuroOasis_Forking_Workflow comprehensive documentation"
      },
      {
        "type": "new",
        "description": "Surgical repository cleanup template for project migration"
      },
      {
        "type": "improved",
        "description": "Project migration methodology with step-by-step workflow"
      },
      {
        "type": "new",
        "description": "GitHub organization transfer and collaboration framework"
      }
    ],
    "created": "2025-05-26T19:35:00.000Z"
  },
  {
    "id": "4",
    "version": "v4.0.0",
    "title": "NodePad Framework Foundation",
    "type": "major",
    "project": "nodepad",
    "date": "2025-05-22",
    "description": "Complete NodePad 4.0.0 framework with single-file architecture and production deployments",
    "changes": [
      {
        "type": "new",
        "description": "Single HTML file architecture with zero external dependencies"
      },
      {
        "type": "new",
        "description": "DOM-as-Truth pattern implementation"
      },
      {
        "type": "new",
        "description": "Recipe Rolodx production deployment with 4x6 printable cards"
      },
      {
        "type": "new",
        "description": "Idea Capture with auto-categorization and cross-device functionality"
      }
    ],
    "created": "2025-05-26T19:35:00.000Z"
  }
]